{
  "name": "City GYM Stip",
  "short_name": "City GYM",
  "description": "Your personal fitness companion for tracking workouts and achieving your goals",
  "start_url": "/",
  "display": "standalone",
  "background_color": "#041047",
  "theme_color": "#ea3363",
  "orientation": "portrait",
  "icons": [
    {
      "src": "/icons/city_gym_stip/icon-192.png",
      "sizes": "192x192",
      "type": "image/png",
      "purpose": "any"
    },
    {
      "src": "/icons/city_gym_stip/icon-512.png",
      "sizes": "512x512",
      "type": "image/png",
      "purpose": "any"
    }
  ]
}
